{
    "layers": [
        {
            "score": 0,
            "miss": 0,
            "scorestogo": 0,
            "conflicts": 0,
            "done": 8290,
            "togo": 0,
            "cpu": 1814698,
            "time": 871635,
            "certtime": 0,
            "news": 0,
            "wrong": 0
        },
        {
            "score": 0,
            "miss": 0,
            "scorestogo": 0,
            "conflicts": 0,
            "done": 3316,
            "togo": 0,
            "cpu": 1079624,
            "time": 304776,
            "certtime": 0,
            "news": 0,
            "wrong": 0
        }
    ],
    "participants": {
        "790115": {
            "score": 176,
            "miss": 1482,
            "scorestogo": 0,
            "conflicts": 0,
            "done": 1658,
            "togo": 0,
            "cpu": 692768,
            "time": 437980,
            "certtime": 0,
            "news": 0,
            "wrong": 0,
            "layer": 0,
            "solver": "MU-TERM 6.1c",
            "solver id": "47423",
            "configuration": "default",
            "CERTIFIED YES": 0,
            "CERTIFIED NO": 0,
            "CERTIFIED UP": 0,
            "CERTIFIED LOW": 0,
            "YES": 175,
            "SAST": 0,
            "PAST": 0,
            "AST": 0,
            "NO": 1,
            "UP": 0,
            "LOW": 0,
            "MAYBE": 56,
            "timeout": 1426,
            "error": 0,
            "normalized": 0.10830769230769231
        },
        "790086": {
            "score": 222,
            "miss": 1436,
            "scorestogo": 0,
            "conflicts": 0,
            "done": 1658,
            "togo": 0,
            "cpu": 189124,
            "time": 182874,
            "certtime": 0,
            "news": 0,
            "wrong": 0,
            "layer": 0,
            "solver": "NaTT",
            "solver id": "47457",
            "configuration": "default",
            "CERTIFIED YES": 0,
            "CERTIFIED NO": 0,
            "CERTIFIED UP": 0,
            "CERTIFIED LOW": 0,
            "YES": 220,
            "SAST": 0,
            "PAST": 0,
            "AST": 0,
            "NO": 2,
            "UP": 0,
            "LOW": 0,
            "MAYBE": 859,
            "timeout": 577,
            "error": 0,
            "normalized": 0.1366153846153846
        },
        "788343": {
            "score": 1590,
            "miss": 68,
            "scorestogo": 0,
            "conflicts": 0,
            "done": 1658,
            "togo": 0,
            "cpu": 104565,
            "time": 35313,
            "certtime": 0,
            "news": 0,
            "wrong": 0,
            "layer": 0,
            "solver": "matchbox-2024-06-19",
            "solver id": "47363",
            "configuration": "s6.sh",
            "CERTIFIED YES": 0,
            "CERTIFIED NO": 0,
            "CERTIFIED UP": 0,
            "CERTIFIED LOW": 0,
            "YES": 1406,
            "SAST": 0,
            "PAST": 0,
            "AST": 0,
            "NO": 184,
            "UP": 0,
            "LOW": 0,
            "MAYBE": 0,
            "timeout": 68,
            "error": 0,
            "normalized": 0.9784615384615385
        },
        "790593": {
            "score": 1145,
            "miss": 513,
            "scorestogo": 0,
            "conflicts": 0,
            "done": 1658,
            "togo": 0,
            "cpu": 647386,
            "time": 168803,
            "certtime": 0,
            "news": 0,
            "wrong": 0,
            "layer": 0,
            "solver": "AProVE24_Fixed",
            "solver id": "47529",
            "configuration": "TRS_full",
            "CERTIFIED YES": 0,
            "CERTIFIED NO": 0,
            "CERTIFIED UP": 0,
            "CERTIFIED LOW": 0,
            "YES": 1028,
            "SAST": 0,
            "PAST": 0,
            "AST": 0,
            "NO": 117,
            "UP": 0,
            "LOW": 0,
            "MAYBE": 0,
            "timeout": 513,
            "error": 0,
            "normalized": 0.7046153846153846
        },
        "788390": {
            "score": 1542,
            "miss": 116,
            "scorestogo": 0,
            "conflicts": 0,
            "done": 1658,
            "togo": 0,
            "cpu": 180855,
            "time": 46665,
            "certtime": 0,
            "news": 0,
            "wrong": 0,
            "layer": 0,
            "solver": "MnM3.23.1",
            "solver id": "47392",
            "configuration": "default",
            "CERTIFIED YES": 0,
            "CERTIFIED NO": 0,
            "CERTIFIED UP": 0,
            "CERTIFIED LOW": 0,
            "YES": 1360,
            "SAST": 0,
            "PAST": 0,
            "AST": 0,
            "NO": 182,
            "UP": 0,
            "LOW": 0,
            "MAYBE": 0,
            "timeout": 115,
            "error": 0,
            "memout": 1,
            "normalized": 0.9489230769230769
        },
        "790604": {
            "score": 957,
            "miss": 701,
            "scorestogo": 0,
            "conflicts": 0,
            "done": 1658,
            "togo": 0,
            "cpu": 864369,
            "time": 226032,
            "certtime": 1570.4299999999957,
            "news": 0,
            "wrong": 0,
            "layer": 1,
            "solver": "AProVE24_Fixed",
            "solver id": "47529",
            "configuration": "certified",
            "CERTIFIED YES": 839,
            "CERTIFIED NO": 118,
            "CERTIFIED UP": 0,
            "CERTIFIED LOW": 0,
            "YES": 0,
            "SAST": 0,
            "PAST": 0,
            "AST": 0,
            "NO": 0,
            "UP": 0,
            "LOW": 0,
            "MAYBE": 66,
            "timeout": 635,
            "error": 0,
            "normalized": 0.5889230769230769
        },
        "788346": {
            "score": 1487,
            "miss": 171,
            "scorestogo": 0,
            "conflicts": 0,
            "done": 1658,
            "togo": 0,
            "cpu": 215255,
            "time": 78744,
            "certtime": 2659.6800000000076,
            "news": 0,
            "wrong": 0,
            "layer": 1,
            "solver": "matchbox-2024-06-19",
            "solver id": "47363",
            "configuration": "s6-cert.sh",
            "CERTIFIED YES": 1304,
            "CERTIFIED NO": 183,
            "CERTIFIED UP": 0,
            "CERTIFIED LOW": 0,
            "YES": 0,
            "SAST": 0,
            "PAST": 0,
            "AST": 0,
            "NO": 0,
            "UP": 0,
            "LOW": 0,
            "MAYBE": 1,
            "timeout": 154,
            "error": 0,
            "normalized": 0.9150769230769231
        }
    },
    "conflicting": false
}