{
    "layers": [
        {
            "score": 0,
            "miss": 0,
            "scorestogo": 0,
            "conflicts": 0,
            "done": 1209,
            "togo": 0,
            "cpu": 399500,
            "time": 145998,
            "certtime": 0,
            "news": 0,
            "wrong": 0
        },
        {
            "score": 0,
            "miss": 0,
            "scorestogo": 0,
            "conflicts": 0,
            "done": 806,
            "togo": 0,
            "cpu": 221290,
            "time": 69547,
            "certtime": 0,
            "news": 0,
            "wrong": 0
        }
    ],
    "participants": {
        "788345": {
            "score": 362,
            "miss": 41,
            "scorestogo": 0,
            "conflicts": 0,
            "done": 403,
            "togo": 0,
            "cpu": 37241,
            "time": 16527,
            "certtime": 0,
            "news": 37,
            "wrong": 0,
            "layer": 0,
            "solver": "matchbox-2024-06-19",
            "solver id": "47363",
            "configuration": "s5.sh",
            "CERTIFIED YES": 0,
            "CERTIFIED NO": 0,
            "CERTIFIED UP": 0,
            "CERTIFIED LOW": 0,
            "YES": 352,
            "SAST": 0,
            "PAST": 0,
            "AST": 0,
            "NO": 10,
            "UP": 0,
            "LOW": 0,
            "MAYBE": 0,
            "timeout": 41,
            "error": 0,
            "normalized": 0.9627659574468085
        },
        "788264": {
            "score": 76,
            "miss": 327,
            "scorestogo": 0,
            "conflicts": 0,
            "done": 403,
            "togo": 0,
            "cpu": 250515,
            "time": 100288,
            "certtime": 0,
            "news": 2,
            "wrong": 0,
            "layer": 0,
            "solver": "AProVE24",
            "solver id": "47318",
            "configuration": "TRS_full",
            "CERTIFIED YES": 0,
            "CERTIFIED NO": 0,
            "CERTIFIED UP": 0,
            "CERTIFIED LOW": 0,
            "YES": 74,
            "SAST": 0,
            "PAST": 0,
            "AST": 0,
            "NO": 2,
            "UP": 0,
            "LOW": 0,
            "MAYBE": 0,
            "timeout": 327,
            "error": 0,
            "normalized": 0.20212765957446807
        },
        "788390": {
            "score": 310,
            "miss": 93,
            "scorestogo": 0,
            "conflicts": 0,
            "done": 403,
            "togo": 0,
            "cpu": 111744,
            "time": 29183,
            "certtime": 0,
            "news": 1,
            "wrong": 0,
            "layer": 0,
            "solver": "MnM3.23.1",
            "solver id": "47392",
            "configuration": "default",
            "CERTIFIED YES": 0,
            "CERTIFIED NO": 0,
            "CERTIFIED UP": 0,
            "CERTIFIED LOW": 0,
            "YES": 297,
            "SAST": 0,
            "PAST": 0,
            "AST": 0,
            "NO": 13,
            "UP": 0,
            "LOW": 0,
            "MAYBE": 0,
            "timeout": 57,
            "error": 0,
            "memout": 36,
            "normalized": 0.824468085106383
        },
        "790604": {
            "score": 168,
            "miss": 235,
            "scorestogo": 0,
            "conflicts": 0,
            "done": 403,
            "togo": 0,
            "cpu": 169878,
            "time": 44623,
            "certtime": 36.66999999999997,
            "news": 0,
            "wrong": 0,
            "layer": 1,
            "solver": "AProVE24_Fixed",
            "solver id": "47529",
            "configuration": "certified",
            "CERTIFIED YES": 166,
            "CERTIFIED NO": 2,
            "CERTIFIED UP": 0,
            "CERTIFIED LOW": 0,
            "YES": 0,
            "SAST": 0,
            "PAST": 0,
            "AST": 0,
            "NO": 0,
            "UP": 0,
            "LOW": 0,
            "MAYBE": 117,
            "timeout": 118,
            "error": 0,
            "normalized": 0.44680851063829785
        },
        "788340": {
            "score": 332,
            "miss": 71,
            "scorestogo": 0,
            "conflicts": 0,
            "done": 403,
            "togo": 0,
            "cpu": 51412,
            "time": 24924,
            "certtime": 3611.0300000000034,
            "news": 34,
            "wrong": 0,
            "layer": 1,
            "solver": "matchbox-2024-06-19",
            "solver id": "47363",
            "configuration": "s5-cert.sh",
            "CERTIFIED YES": 325,
            "CERTIFIED NO": 7,
            "CERTIFIED UP": 0,
            "CERTIFIED LOW": 0,
            "YES": 0,
            "SAST": 0,
            "PAST": 0,
            "AST": 0,
            "NO": 0,
            "UP": 0,
            "LOW": 0,
            "MAYBE": 0,
            "timeout": 54,
            "error": 0,
            "normalized": 0.8829787234042553
        }
    },
    "conflicting": false
}